<annotation>
	<folder>cat</folder>
	<filename>000019.JPG</filename>
	<path>C:\training\pyworkspace\ObjectDetection\cimgs\cat\000019.JPG</path>
	<source>
		<database>Unknown</database>
	</source>
	<size>
		<width>2160</width>
		<height>1648</height>
		<depth>3</depth>
	</size>
	<segmented>0</segmented>
	<object>
		<name>cat-face</name>
		<pose>Unspecified</pose>
		<truncated>0</truncated>
		<difficult>0</difficult>
		<bndbox>
			<xmin>708</xmin>
			<ymin>524</ymin>
			<xmax>1114</xmax>
			<ymax>1045</ymax>
		</bndbox>
	</object>
	<object>
		<name>cat</name>
		<pose>Unspecified</pose>
		<truncated>0</truncated>
		<difficult>0</difficult>
		<bndbox>
			<xmin>694</xmin>
			<ymin>515</ymin>
			<xmax>1859</xmax>
			<ymax>1617</ymax>
		</bndbox>
	</object>
</annotation>
